LICENSE
MANIFEST.in
README.rst
django_shortcuts.py
setup.py
django_shortcuts.egg-info/PKG-INFO
django_shortcuts.egg-info/SOURCES.txt
django_shortcuts.egg-info/dependency_links.txt
django_shortcuts.egg-info/entry_points.txt
django_shortcuts.egg-info/top_level.txt