Metadata-Version: 1.0
Name: django-shortcuts
Version: 1.4
Summary: You spend way too much time typing 'python manage.py'
Home-page: http://github.com/jgorset/django-shortcuts
Author: Johannes Gorset
Author-email: jgorset@gmail.com
License: UNKNOWN
Platform: UNKNOWN
Classifier: Development Status :: 5 - Production/Stable
Classifier: Intended Audience :: Developers
Classifier: Natural Language :: English
Classifier: License :: OSI Approved :: MIT License
Classifier: Programming Language :: Python
Classifier: Programming Language :: Python :: 2.6
Classifier: Programming Language :: Python :: 2.7
